take_photo/__init__.py
take_photo/__main__.py
take_photo/take_photo.py
take_photo-1.0.2.dist-info/LICENSE
take_photo-1.0.2.dist-info/METADATA
take_photo-1.0.2.dist-info/WHEEL
take_photo-1.0.2.dist-info/top_level.txt
take_photo-1.0.2.dist-info/RECORD
